{
  "result": {
    "1": [
      {
        "1": "Sal Island Amilcar Cabral International, Cape Verde (SID)",
        "2": "airport",
        "3": "SID",
        "4": "SID",
        "5": "Sal",
        "6": -22.949444,
        "7": 16.7413889,
        "10": "Atlantic/Cape_Verde"
      },
      {
        "1": "Sidney Richland Municipal, MT (SDY)",
        "2": "airport",
        "3": "SDY",
        "4": "SDY",
        "5": "Sidney",
        "6": -104.19639,
        "7": 47.705,
        "10": "America/Denver"
      },
      {
        "1": "Touggourt Sidi Mahdi, Algeria (TGR)",
        "2": "airport",
        "3": "TGR",
        "4": "TGR",
        "5": "Touggourt",
        "6": 6.08861111,
        "7": 33.0677778,
        "10": "Africa/Algiers"
      }
    ]
  }
}